__init__.py
grams.py
grams_pytorch-0.0.2.dist-info/METADATA
grams_pytorch-0.0.2.dist-info/WHEEL
grams_pytorch-0.0.2.dist-info/top_level.txt
grams_pytorch-0.0.2.dist-info/RECORD
